handroll/__init__.py
handroll/configuration.py
handroll/date.py
handroll/director.py
handroll/entry.py
handroll/exceptions.py
handroll/handlers.py
handroll/i18n.py
handroll/resolver.py
handroll/scaffolder.py
handroll/server.py
handroll/signals.py
handroll/site.py
handroll/commands/__init__.py
handroll/commands/base.py
handroll/commands/build.py
handroll/commands/builtins.py
handroll/commands/scaffold.py
handroll/commands/watch.py
handroll/composers/__init__.py
handroll/composers/atom.py
handroll/composers/generic.py
handroll/composers/j2.py
handroll/composers/md.py
handroll/composers/mixins.py
handroll/composers/rst.py
handroll/composers/sass.py
handroll/composers/txt.py
handroll/extensions/__init__.py
handroll/extensions/base.py
handroll/extensions/blog.py
handroll/extensions/loader.py
handroll/extensions/sitemap.py
handroll/locale/handroll.pot
handroll/locale/ar/LC_MESSAGES/handroll.mo
handroll/locale/ar/LC_MESSAGES/handroll.po
handroll/locale/de/LC_MESSAGES/handroll.mo
handroll/locale/de/LC_MESSAGES/handroll.po
handroll/locale/el/LC_MESSAGES/handroll.mo
handroll/locale/el/LC_MESSAGES/handroll.po
handroll/locale/es/LC_MESSAGES/handroll.mo
handroll/locale/es/LC_MESSAGES/handroll.po
handroll/locale/fr/LC_MESSAGES/handroll.mo
handroll/locale/fr/LC_MESSAGES/handroll.po
handroll/locale/it/LC_MESSAGES/handroll.mo
handroll/locale/it/LC_MESSAGES/handroll.po
handroll/locale/nl/LC_MESSAGES/handroll.mo
handroll/locale/nl/LC_MESSAGES/handroll.po
handroll/locale/pt_BR/LC_MESSAGES/handroll.mo
handroll/locale/pt_BR/LC_MESSAGES/handroll.po
handroll/scaffolds/default/handroll.conf
handroll/scaffolds/default/index.md
handroll/scaffolds/default/style.css
handroll/scaffolds/default/templates/base.j2
handroll/template/__init__.py
handroll/template/catalog.py
handroll/template/j2.py
handroll/tests/__init__.py
handroll/tests/factory.py
handroll/tests/test_blog_extension.py
handroll/tests/test_commands.py
handroll-3.1.dist-info/DESCRIPTION.rst
handroll-3.1.dist-info/LICENSE.txt
handroll-3.1.dist-info/METADATA
handroll-3.1.dist-info/RECORD
handroll-3.1.dist-info/WHEEL
handroll-3.1.dist-info/entry_points.txt
handroll-3.1.dist-info/metadata.json
handroll-3.1.dist-info/pbr.json
handroll-3.1.dist-info/top_level.txt
