Metadata-Version: 2.0
Name: handroll
Version: 3.1
Summary: A website generator for software artisans
Home-page: http://handroll.github.io
Author: Matt Layman
Author-email: matthewlayman@gmail.com
License: BSD
Keywords: generator,Markdown,ReStructuredText,Textile
Platform: any
Classifier: Development Status :: 5 - Production/Stable
Classifier: Environment :: Console
Classifier: Intended Audience :: Developers
Classifier: Intended Audience :: Education
Classifier: Intended Audience :: Science/Research
Classifier: License :: OSI Approved :: BSD License
Classifier: Operating System :: OS Independent
Classifier: Programming Language :: Python :: 2.7
Classifier: Programming Language :: Python :: 3.3
Classifier: Programming Language :: Python :: 3.4
Classifier: Programming Language :: Python :: Implementation :: PyPy
Classifier: Topic :: Artistic Software
Classifier: Topic :: Documentation
Classifier: Topic :: Internet :: WWW/HTTP :: Site Management
Classifier: Topic :: Office/Business :: News/Diary
Classifier: Topic :: Software Development :: Documentation
Classifier: Topic :: Text Processing :: Markup :: HTML
Requires-Dist: Jinja2
Requires-Dist: Markdown
Requires-Dist: PyYAML
Requires-Dist: Pygments
Requires-Dist: blinker
Requires-Dist: docutils
Requires-Dist: mock
Requires-Dist: smartypants
Requires-Dist: textile
Requires-Dist: watchdog
Requires-Dist: werkzeug
